yaqd_scpi/VERSION
yaqd_scpi/__init__.py
yaqd_scpi/__version__.py
yaqd_scpi/_scpi_sensor.py
yaqd_scpi/_scpi_set_continuous.py
yaqd_scpi/_scpi_set_discrete.py
yaqd_scpi/scpi-sensor.avpr
yaqd_scpi/scpi-sensor.toml
yaqd_scpi/scpi-set-continuous.avpr
yaqd_scpi/scpi-set-continuous.toml
yaqd_scpi/scpi-set-discrete.avpr
yaqd_scpi/scpi-set-discrete.toml
yaqd_scpi-2021.11.0.dist-info/entry_points.txt
yaqd_scpi-2021.11.0.dist-info/LICENSE
yaqd_scpi-2021.11.0.dist-info/WHEEL
yaqd_scpi-2021.11.0.dist-info/METADATA
yaqd_scpi-2021.11.0.dist-info/RECORD
