Metadata-Version: 2.1
Name: yaqd-scpi
Version: 2021.11.0
Summary: yaq daemons for SCPI hardware
Home-page: https://yaq.fyi
Author: Blaise Thompson
Author-email: blaise@untzag.com
Requires-Python: >=3.7
Classifier: Development Status :: 3 - Alpha
Classifier: Intended Audience :: Science/Research
Classifier: License :: OSI Approved :: GNU Lesser General Public License v3 (LGPLv3)
Classifier: Natural Language :: English
Classifier: Programming Language :: Python :: 3
Classifier: Programming Language :: Python :: 3.7
Classifier: Programming Language :: Python :: 3.8
Classifier: Programming Language :: Python :: 3.9
Classifier: Topic :: Scientific/Engineering
Requires-Dist: yaqd-core>=2020.10.0
Requires-Dist: PyVISA
Requires-Dist: PyVISA-py
Requires-Dist: black ; extra == "dev"
Requires-Dist: pre-commit ; extra == "dev"
Project-URL: Issues, https://gitlab.com/yaq/yaqd-scpi/issues
Project-URL: Source, https://gitlab.com/yaq/yaqd-scpi
Provides-Extra: dev
